proxyup/__init__.py
proxyup/proxy_retriever.py
tests/__init__.py
tests/test_proxyupretriever.py
proxyup-0.0.6.dist-info/LICENSE
proxyup-0.0.6.dist-info/METADATA
proxyup-0.0.6.dist-info/WHEEL
proxyup-0.0.6.dist-info/entry_points.txt
proxyup-0.0.6.dist-info/top_level.txt
proxyup-0.0.6.dist-info/RECORD
