Metadata-Version: 2.1
Name: proxyup
Version: 0.0.6
Summary: Proxy updater
Home-page: UNKNOWN
Author: Iván de Paz Centeno
Author-email: ipazc@unileon.es
License: UNKNOWN
Keywords: proxy api check list free
Platform: UNKNOWN
Classifier: Development Status :: 1 - Planning
Classifier: Environment :: Console
Classifier: Intended Audience :: Developers
Classifier: Intended Audience :: Education
Classifier: Natural Language :: English
Classifier: Operating System :: POSIX :: Linux
Classifier: Programming Language :: Python :: 3.4
Classifier: Programming Language :: Python :: 3.5
Classifier: Programming Language :: Python :: 3.6
Classifier: Programming Language :: Python :: 3.7
Requires-Dist: requests
Requires-Dist: pandas
